__init__.py
configus.py
tests.py
configus/__init__.py
configus/configus.py
configus/test_main.py
configus/tests.py
configus-0.1.2.dist-info/DESCRIPTION.rst
configus-0.1.2.dist-info/METADATA
configus-0.1.2.dist-info/RECORD
configus-0.1.2.dist-info/WHEEL
configus-0.1.2.dist-info/metadata.json
configus-0.1.2.dist-info/top_level.txt
